pip2conda/__init__.py
pip2conda/__main__.py
pip2conda/_version.py
pip2conda/pip2conda.py
pip2conda/tests/__init__.py
pip2conda/tests/test_pip2conda.py
pip2conda-0.9.0.dist-info/licenses/LICENSE
pip2conda-0.9.0.dist-info/METADATA
pip2conda-0.9.0.dist-info/WHEEL
pip2conda-0.9.0.dist-info/entry_points.txt
pip2conda-0.9.0.dist-info/top_level.txt
pip2conda-0.9.0.dist-info/RECORD
