Metadata-Version: 2.4
Name: pip2conda
Version: 0.9.0
Summary: Translate pip requirements into conda requirements
Author-email: Duncan Macleod <duncanmmacleod@gmail.com>
License: GPL-3.0-or-later
Project-URL: Bug Tracker, https://gitlab.com/gwpy/pip2conda/-/issues
Project-URL: Documentation, https://pip2conda.readthedocs.io
Project-URL: Homepage, https://gitlab.com/gwpy/pip2conda/
Project-URL: Source Code, https://gitlab.com/gwpy/pip2conda.git
Classifier: Development Status :: 4 - Beta
Classifier: Intended Audience :: Developers
Classifier: License :: OSI Approved :: GNU General Public License v3 or later (GPLv3+)
Classifier: Natural Language :: English
Classifier: Operating System :: OS Independent
Classifier: Programming Language :: Python
Classifier: Programming Language :: Python :: 3
Classifier: Programming Language :: Python :: 3.10
Classifier: Programming Language :: Python :: 3.11
Classifier: Programming Language :: Python :: 3.12
Classifier: Programming Language :: Python :: 3.13
Classifier: Topic :: Software Development
Classifier: Topic :: Software Development :: Build Tools
Classifier: Topic :: Software Development :: Testing
Requires-Python: >=3.10
License-File: LICENSE
Requires-Dist: build>=1.0.0
Requires-Dist: grayskull>=1.0.0
Requires-Dist: requests>=2.32.5
Requires-Dist: ruamel.yaml>=0.18.15
Requires-Dist: packaging>=25.0
Requires-Dist: tomli>=2.2.1; python_version < "3.11"
Requires-Dist: wheel>=0.45.1
Dynamic: license-file
